HerdingCats/__init__.py
HerdingCats/config/__init__.py
HerdingCats/config/source_endpoints.py
HerdingCats/config/sources.py
HerdingCats/errors/__init__.py
HerdingCats/errors/errors.py
HerdingCats/explorer/__init__.py
HerdingCats/explorer/explore.py
HerdingCats/llm/__init__.py
HerdingCats/llm/llm_config.py
HerdingCats/llm/llm_summary.py
HerdingCats/loader/__init__.py
HerdingCats/loader/loader.py
HerdingCats/loader/loader_stores.py
HerdingCats/session/__init__.py
HerdingCats/session/session.py
herdcats-0.1.4.dist-info/LICENSE
herdcats-0.1.4.dist-info/METADATA
herdcats-0.1.4.dist-info/WHEEL
herdcats-0.1.4.dist-info/RECORD
